counter_4bit.v
module counter_4bit (
    input clk,
    input reset,
    output reg [3:0] count
);

always @(posedge clk or posedge reset) begin
    if(reset)
    count <= 4'b0000;
    else
    count <= count +1;
end
endmodule

tb_counter_v2.v
`timescale 1ns/1ps

module tb_counter_v2;

reg clk;
reg reset;
wire [3:0] count;

// Instantiate DUT(Design Under Test)
counter_4bit uut(
    .clk(clk),
    .reset(reset),
    .count(count)
);

//Clock generation
always #5 clk=~clk;

initial begin
    $dumpfile("counter_v2.vcd");
    $dumpvars(0,tb_counter_v2);

    //Initial state
    clk=0;
    reset=1;

    // Hold for some time
    #10 reset=0;

    // Let counter run
    #40;

    // Apply reset again mid-operation
    reset=1;
    #10
    reset=0;

    //Let it run again
    #50;

    //Reset again quickly
    reset=1;
    #5;
    reset=0;

    #50;
    $finish;
end
endmodule

counter_v2.vcd
$date
	Tue Apr 14 12:51:49 2026
$end
$version
	Icarus Verilog
$end
$timescale
	1ps
$end
$scope module tb_counter_v2 $end
$var wire 4 ! count [3:0] $end
$var reg 1 " clk $end
$var reg 1 # reset $end
$scope module uut $end
$var wire 1 " clk $end
$var wire 1 # reset $end
$var reg 4 $ count [3:0] $end
$upscope $end
$upscope $end
$enddefinitions $end
#0
$dumpvars
b0 $
1#
0"
b0 !
$end
#5000
1"
#10000
0"
0#
#15000
b1 !
b1 $
1"
#20000
0"
#25000
b10 !
b10 $
1"
#30000
0"
#35000
b11 !
b11 $
1"
#40000
0"
#45000
b100 !
b100 $
1"
#50000
b0 !
b0 $
0"
1#
#55000
1"
#60000
0"
0#
#65000
b1 !
b1 $
1"
#70000
0"
#75000
b10 !
b10 $
1"
#80000
0"
#85000
b11 !
b11 $
1"
#90000
0"
#95000
b100 !
b100 $
1"
#100000
0"
#105000
b101 !
b101 $
1"
#110000
b0 !
b0 $
0"
1#
#115000
b1 !
b1 $
1"
0#
#120000
0"
#125000
b10 !
b10 $
1"
#130000
0"
#135000
b11 !
b11 $
1"
#140000
0"
#145000
b100 !
b100 $
1"
#150000
0"
#155000
b101 !
b101 $
1"
#160000
0"
#165000
b110 !
b110 $
1"
