counter_4bit_with_enable.v
module counter_4bit_with_enable(
    input clk,
    input reset,
    input enable,
    output reg[3:0] count
);

always @(posedge clk or posedge reset) begin
    if(reset)
    count <= 4'b0000;
    else if(enable)
    count <= count + 1;
    else
    count <= count; // Hold Value
end
endmodule

tb_counter_with_enable.v
`timescale 1ns/1ps

module tb_counter_with_enable;

reg clk;
reg reset;
reg enable;
wire [3:0] count;

counter_4bit_with_enable uut(
    .clk(clk),
    .reset(reset),
    .enable(enable),
    .count(count)
);

// Clock
always #5 clk=~clk;

initial begin
    $dumpfile("counter_enable.vcd");
    $dumpvars(0, tb_counter_with_enable);

    clk=0;
    reset=1;
    enable=0;

    #10 reset=0;

    //Enable counting
    enable=1;
    #40;

    // Disable counting(should Freeze)
    enable=0;
    #30;

    //Enable again
    enable=1;
    #40;

    $finish;
end
endmodule

counter_enable.vcd
$date
	Tue Apr 14 16:38:47 2026
$end
$version
	Icarus Verilog
$end
$timescale
	1ps
$end
$scope module tb_counter_with_enable $end
$var wire 4 ! count [3:0] $end
$var reg 1 " clk $end
$var reg 1 # enable $end
$var reg 1 $ reset $end
$scope module uut $end
$var wire 1 " clk $end
$var wire 1 # enable $end
$var wire 1 $ reset $end
$var reg 4 % count [3:0] $end
$upscope $end
$upscope $end
$enddefinitions $end
#0
$dumpvars
b0 %
1$
0#
0"
b0 !
$end
#5000
1"
#10000
0"
1#
0$
#15000
b1 !
b1 %
1"
#20000
0"
#25000
b10 !
b10 %
1"
#30000
0"
#35000
b11 !
b11 %
1"
#40000
0"
#45000
b100 !
b100 %
1"
#50000
0"
0#
#55000
1"
#60000
0"
#65000
1"
#70000
0"
#75000
1"
#80000
0"
1#
#85000
b101 !
b101 %
1"
#90000
0"
#95000
b110 !
b110 %
1"
#100000
0"
#105000
b111 !
b111 %
1"
#110000
0"
#115000
b1000 !
b1000 %
1"
