parameterize_counter/counter.v
module counter #(
    parameter WIDTH = 4
)
(
    input clk,
    input reset,
    input enable,
    output reg [WIDTH-1:0] count
);

always @(posedge clk or posedge reset) begin
    if(reset)
    count <= {WIDTH{1'b0}}; // reset to 0 (generic)
    else if(enable)
    count <= count + 1;
    else
    count <= count;
end
endmodule

parameterize_counter/tb_counter.v
`timescale 1ns/1ps

module tb_counter;

reg clk;
reg reset;
reg enable;
wire[7:0] count;    // testing 8-bit

//Instantiate with WIDTH = 8
counter #(.WIDTH(8)) uut(
    .clk(clk),
    .reset(reset),
    .enable(enable),
    .count(count)
);

//Clock

always #5 clk = ~clk;

initial begin
    $dumpfile("counter_param.vcd");
    $dumpvars(0, tb_counter);

    clk=0;
    reset=1;
    enable=0;

    #10 reset=0;

    enable = 1;
    #100;

    enable = 0;
    #30;

    enable = 1;
    #50;

    $finish;
end
endmodule

parameterize_counter/counter_param.vcd
$date
	Tue Apr 14 17:29:01 2026
$end
$version
	Icarus Verilog
$end
$timescale
	1ps
$end
$scope module tb_counter $end
$var wire 8 ! count [7:0] $end
$var reg 1 " clk $end
$var reg 1 # enable $end
$var reg 1 $ reset $end
$scope module uut $end
$var wire 1 " clk $end
$var wire 1 # enable $end
$var wire 1 $ reset $end
$var reg 8 % count [7:0] $end
$upscope $end
$upscope $end
$enddefinitions $end
#0
$dumpvars
b0 %
1$
0#
0"
b0 !
$end
#5000
1"
#10000
0"
1#
0$
#15000
b1 !
b1 %
1"
#20000
0"
#25000
b10 !
b10 %
1"
#30000
0"
#35000
b11 !
b11 %
1"
#40000
0"
#45000
b100 !
b100 %
1"
#50000
0"
#55000
b101 !
b101 %
1"
#60000
0"
#65000
b110 !
b110 %
1"
#70000
0"
#75000
b111 !
b111 %
1"
#80000
0"
#85000
b1000 !
b1000 %
1"
#90000
0"
#95000
b1001 !
b1001 %
1"
#100000
0"
#105000
b1010 !
b1010 %
1"
#110000
0"
0#
#115000
1"
#120000
0"
#125000
1"
#130000
0"
#135000
1"
#140000
0"
1#
#145000
b1011 !
b1011 %
1"
#150000
0"
#155000
b1100 !
b1100 %
1"
#160000
0"
#165000
b1101 !
b1101 %
1"
#170000
0"
#175000
b1110 !
b1110 %
1"
#180000
0"
#185000
b1111 !
b1111 %
1"
